AUTHORS
LICENSE
MANIFEST.in
VERSION
requirements.txt
setup.py
django_pg/VERSION
django_pg/__init__.py
django_pg/management.py
django_pg/models/__init__.py
django_pg/models/base.py
django_pg/models/query.py
django_pg/models/fields/__init__.py
django_pg/models/fields/array.py
django_pg/models/fields/datetime_.py
django_pg/models/fields/json.py
django_pg/models/fields/uuid.py
django_pg/models/fields/composite/__init__.py
django_pg/models/fields/composite/adapter.py
django_pg/models/fields/composite/meta.py
django_pg/models/sql/__init__.py
django_pg/models/sql/query.py
django_pg/models/sql/where.py
django_pg/utils/__init__.py
django_pg/utils/context.py
django_pg/utils/datatypes.py
django_pg/utils/decorators.py
django_pg/utils/gis.py
django_pg/utils/repr.py
django_pg/utils/south.py
django_pg/utils/types.py
django_pg/utils/utf8.py
django_pgfields.egg-info/PKG-INFO
django_pgfields.egg-info/SOURCES.txt
django_pgfields.egg-info/dependency_links.txt
django_pgfields.egg-info/requires.txt
django_pgfields.egg-info/top_level.txt
docs/Makefile
docs/composite.rst
docs/conf.py
docs/fields.rst
docs/index.rst
docs/misc.rst
docs/settings.rst
docs/usage.rst
docs/_ext/pgfields_docs.py
docs/_ext/__pycache__/pgfields_docs.cpython-34.pyc
docs/_static/pgfields.css
docs/_templates/layout.html
docs/releases/0.9.2.rst
docs/releases/1.0.rst
docs/releases/1.1.rst
docs/releases/1.2.rst
docs/releases/1.3.rst
docs/releases/1.4.rst
docs/releases/index.rst