Metadata-Version: 1.1
Name: django-pgfields
Version: 1.4.4
Summary: Provides custom Field subclasses intended for use with types available in PostgreSQL but not in the Django core ORM, including arrays and composite types. For Python 2 or Python 3.
Home-page: https://github.com/lukesneeringer/django-pgfields
Author: Luke Sneeringer
Author-email: luke@sneeringer.com
License: New BSD
Platform: UNKNOWN
Classifier: Development Status :: 5 - Production/Stable
Classifier: Environment :: Web Environment
Classifier: Framework :: Django
Classifier: Intended Audience :: Developers
Classifier: License :: OSI Approved :: BSD License
Classifier: Operating System :: OS Independent
Classifier: Programming Language :: Python
Classifier: Programming Language :: Python :: 2.7
Classifier: Programming Language :: Python :: 3.3
Classifier: Topic :: Database
Classifier: Topic :: Software Development
Provides: django_pg
